{
  "script": "repro_sin2_z6_verify.py",
  "classification": "REPRO",
  "timestamp": "2026-01-25T03:58:35.102685",
  "supports_claims": [
    "E-CH11-Der-005",
    "E-CH11-Der-013"
  ],
  "inputs": {
    "Z6_ORDER": 6,
    "Z2_ORDER": 2,
    "Z3_ORDER": 3
  },
  "subgroup_verification": {
    "z6_elements": [
      0,
      1,
      2,
      3,
      4,
      5
    ],
    "z2_elements": [
      0,
      3
    ],
    "z3_elements": [
      0,
      2,
      4
    ],
    "z2_is_subgroup": true,
    "z3_is_subgroup": true,
    "verification": true
  },
  "coupling_ratio": {
    "g_prime_squared_prop": 2,
    "g_squared_prop": 6,
    "ratio": 0.3333333333333333,
    "expected": 0.3333333333333333,
    "verification": true
  },
  "sin2_method1": {
    "formula": "g'\u00b2/(g\u00b2 + g'\u00b2)",
    "coupling_ratio": 0.3333333333333333,
    "sin2_theta_w": 0.25,
    "expected": 0.25,
    "verification": true
  },
  "sin2_method2": {
    "formula": "|Z\u2082|/(|Z\u2082|+|Z\u2086|)",
    "numerator": 2,
    "denominator": 8,
    "sin2_theta_w": 0.25,
    "expected": 0.25,
    "verification": true
  },
  "experimental_comparison": {
    "sin2_bare": 0.25,
    "pdg_mz": 0.23122,
    "deviation_percent": 8.122134763428765,
    "note": "Bare value differs from M_Z value; RG running needed for comparison"
  },
  "overall_verification": "PASS"
}