{
  "artifact_class": "CONDITIONAL [Dc]",
  "sprint": "OPEN-22-4",
  "date": "2026-01-25",
  "description": "Physical V(xi) + G_eff from OPR-01/21/22 pipeline",
  "derivation_chain": {
    "V_eff": {
      "status": "[Dc] DERIVED",
      "source": "OPR-21 L2: 5D Dirac reduction",
      "formula": "V_L = M\u00b2 - M' (flat space, left-handed)"
    },
    "M0": {
      "status": "[Dc] DERIVED",
      "source": "OPR-01 Lemma 4: sigma anchor",
      "formula": "M\u2080\u00b2 = (3/4) y\u00b2 \u03c3 \u0394"
    },
    "f1_extraction": {
      "status": "[Dc] DERIVED",
      "source": "OPEN-22-1: BVP mode extraction",
      "conversion": "|f\u2081(0)|\u00b2 = |f\u0303\u2081(0)|\u00b2 \u00d7 \u2113 (natural from unit)"
    },
    "G_eff": {
      "status": "[Dc] DERIVED",
      "source": "OPR-22 L9",
      "formula": "G_eff = g\u2085\u00b2\u2113|f\u2081(0)|\u00b2/(2x\u2081\u00b2)"
    }
  },
  "parameters_postulated": {
    "sigma": "[P] membrane tension",
    "Delta": "[P] domain wall width",
    "ell": "[P] domain size (or n = \u2113/\u0394)",
    "y": "[P] Yukawa coupling",
    "g5": "[P] 5D gauge coupling"
  },
  "mu_scan": {
    "mu_values": [
      5,
      10,
      15,
      20,
      25,
      27,
      30,
      32,
      35,
      40,
      50
    ],
    "n_bound_3_regime": {
      "achieved": true,
      "mu_range": [
        10.0,
        10.0
      ]
    },
    "results": [
      {
        "mu": 5.0,
        "sigma": 2.0833333333333335,
        "Delta": 1.0,
        "sigma_Delta": 2.0833333333333335,
        "n": 4.0,
        "ell": 4.0,
        "y": 1.0,
        "M0": 1.25,
        "V_asymptotic": 1.5625,
        "n_bound": 2,
        "x1": 4.6991644325802175,
        "f1_at_0_squared": 1.541621794214258,
        "Geff_over_g5sq_ell": 0.034906520606568396,
        "Ceff_over_g5sq_ell": 0.04528545293997966,
        "Geff_factor": 0.034906520606568396,
        "regime": "N=2"
      },
      {
        "mu": 10.0,
        "sigma": 8.333333333333334,
        "Delta": 1.0,
        "sigma_Delta": 8.333333333333334,
        "n": 4.0,
        "ell": 4.0,
        "y": 1.0,
        "M0": 2.5,
        "V_asymptotic": 6.25,
        "n_bound": 3,
        "x1": 7.772724837765227,
        "f1_at_0_squared": 0.5748538275067776,
        "Geff_over_g5sq_ell": 0.0047575224314336355,
        "Ceff_over_g5sq_ell": 0.016552111871874223,
        "Geff_factor": 0.0047575224314336355,
        "regime": "TARGET"
      },
      {
        "mu": 15.0,
        "sigma": 18.75,
        "Delta": 1.0,
        "sigma_Delta": 18.75,
        "n": 4.0,
        "ell": 4.0,
        "y": 1.0,
        "M0": 3.75,
        "V_asymptotic": 14.0625,
        "n_bound": 4,
        "x1": 10.167585564554843,
        "f1_at_0_squared": 0.06148720707774502,
        "Geff_over_g5sq_ell": 0.0002973850274928488,
        "Ceff_over_g5sq_ell": 0.009673069948252237,
        "Geff_factor": 0.0002973850274928488,
        "regime": "N=4"
      },
      {
        "mu": 20.0,
        "sigma": 33.333333333333336,
        "Delta": 1.0,
        "sigma_Delta": 33.333333333333336,
        "n": 4.0,
        "ell": 4.0,
        "y": 1.0,
        "M0": 5.0,
        "V_asymptotic": 25.0,
        "n_bound": 5,
        "x1": 11.997631350755746,
        "f1_at_0_squared": 0.003747455834124644,
        "Geff_over_g5sq_ell": 1.3017137755790715e-05,
        "Ceff_over_g5sq_ell": 0.006947186748543146,
        "Geff_factor": 1.3017137755790715e-05,
        "regime": "N=5"
      },
      {
        "mu": 25.0,
        "sigma": 52.083333333333336,
        "Delta": 1.0,
        "sigma_Delta": 52.083333333333336,
        "n": 4.0,
        "ell": 4.0,
        "y": 1.0,
        "M0": 6.25,
        "V_asymptotic": 39.0625,
        "n_bound": 6,
        "x1": 13.564434199466934,
        "f1_at_0_squared": 0.00019737200532997948,
        "Geff_over_g5sq_ell": 5.363548247659972e-07,
        "Ceff_over_g5sq_ell": 0.005434963523517775,
        "Geff_factor": 5.363548247659972e-07,
        "regime": "N=6"
      },
      {
        "mu": 27.0,
        "sigma": 60.75,
        "Delta": 1.0,
        "sigma_Delta": 60.75,
        "n": 4.0,
        "ell": 4.0,
        "y": 1.0,
        "M0": 6.75,
        "V_asymptotic": 45.5625,
        "n_bound": 6,
        "x1": 14.141995353401025,
        "f1_at_0_squared": 5.946409473310113e-05,
        "Geff_over_g5sq_ell": 1.4866318588249604e-07,
        "Ceff_over_g5sq_ell": 0.005000099187577191,
        "Geff_factor": 1.4866318588249604e-07,
        "regime": "N=6"
      },
      {
        "mu": 30.0,
        "sigma": 75.0,
        "Delta": 1.0,
        "sigma_Delta": 75.0,
        "n": 4.0,
        "ell": 4.0,
        "y": 1.0,
        "M0": 7.5,
        "V_asymptotic": 56.25,
        "n_bound": 7,
        "x1": 14.966507412534853,
        "f1_at_0_squared": 9.660618093185665e-06,
        "Geff_over_g5sq_ell": 2.156423161889246e-08,
        "Ceff_over_g5sq_ell": 0.004464358576415163,
        "Geff_factor": 2.156423161889246e-08,
        "regime": "N=7"
      },
      {
        "mu": 32.0,
        "sigma": 85.33333333333333,
        "Delta": 1.0,
        "sigma_Delta": 85.33333333333333,
        "n": 4.0,
        "ell": 4.0,
        "y": 1.0,
        "M0": 8.0,
        "V_asymptotic": 64.0,
        "n_bound": 7,
        "x1": 15.4918031277263,
        "f1_at_0_squared": 2.8477968655427144e-06,
        "Geff_over_g5sq_ell": 5.933009906332862e-09,
        "Ceff_over_g5sq_ell": 0.004166736734715935,
        "Geff_factor": 5.933009906332862e-09,
        "regime": "N=7"
      },
      {
        "mu": 35.0,
        "sigma": 102.08333333333333,
        "Delta": 1.0,
        "sigma_Delta": 102.08333333333333,
        "n": 4.0,
        "ell": 4.0,
        "y": 1.0,
        "M0": 8.75,
        "V_asymptotic": 76.5625,
        "n_bound": 8,
        "x1": 16.247927216516086,
        "f1_at_0_squared": 4.5013186418700873e-07,
        "Geff_over_g5sq_ell": 8.52538168271743e-10,
        "Ceff_over_g5sq_ell": 0.003787948537309295,
        "Geff_factor": 8.52538168271743e-10,
        "regime": "N=8"
      },
      {
        "mu": 40.0,
        "sigma": 133.33333333333334,
        "Delta": 1.0,
        "sigma_Delta": 133.33333333333334,
        "n": 4.0,
        "ell": 4.0,
        "y": 1.0,
        "M0": 10.0,
        "V_asymptotic": 100.0,
        "n_bound": 9,
        "x1": 17.435408570791466,
        "f1_at_0_squared": 2.0241177612804477e-08,
        "Geff_over_g5sq_ell": 3.329212544863203e-11,
        "Ceff_over_g5sq_ell": 0.003289544322517242,
        "Geff_factor": 3.329212544863203e-11,
        "regime": "N=9"
      },
      {
        "mu": 50.0,
        "sigma": 208.33333333333334,
        "Delta": 1.0,
        "sigma_Delta": 208.33333333333334,
        "n": 4.0,
        "ell": 4.0,
        "y": 1.0,
        "M0": 12.5,
        "V_asymptotic": 156.25,
        "n_bound": 10,
        "x1": 19.59564653254774,
        "f1_at_0_squared": 3.799517833850348e-11,
        "Geff_over_g5sq_ell": 4.947425892065462e-14,
        "Ceff_over_g5sq_ell": 0.002604238805244322,
        "Geff_factor": 4.947425892065462e-14,
        "regime": "N=10"
      }
    ]
  },
  "physical_param_scan": {
    "sigma_Delta_values": [
      30,
      50,
      75,
      100,
      150
    ],
    "n_values": [
      3,
      4,
      5
    ],
    "n_bound_3_count": 0,
    "total_configurations": 15
  },
  "key_results_in_target_regime": {
    "mu": 10.0,
    "x1": 7.772724837765227,
    "f1_at_0_squared": 0.5748538275067776,
    "Geff_factor": 0.0047575224314336355,
    "formula": "G_eff = (g\u2085\u00b2\u2113) \u00d7 (Geff_factor)"
  },
  "dimensional_verification": {
    "G_eff_dimension": "L\u00b2 = GeV\u207b\u00b2",
    "status": "PASS"
  },
  "no_smuggling_certification": {
    "NOT_used": [
      "M_W",
      "M_Z",
      "G_F",
      "v=246GeV",
      "sin\u00b2\u03b8_W",
      "\u03b1(M_Z)",
      "PMNS/CKM",
      "\u03c4_n",
      "CODATA"
    ],
    "status": "PASS"
  },
  "closure_status": {
    "OPEN-22-4": "CONDITIONAL [Dc]",
    "condition": "Parameters (\u03c3, \u0394, \u2113, y, g\u2085) remain [P] postulated",
    "upgrade_path": "Derive parameters from independent physics"
  },
  "files_generated": [
    "code/output/open22_4_physical_summary.json",
    "code/output/open22_4_physical_table.md"
  ]
}